{
  "typeConfig": [
    {
      "num": "01",
      "tag": "wait",
      "name": "等待"
    },
    {
      "num": "02",
      "tag": "defend",
      "name": "坚守"
    },
    {
      "num": "03",
      "tag": "charge",
      "name": "冲锋"
    },
    {
      "num": "04",
      "tag": "shoot",
      "name": "射击"
    },
    {
      "num": "05",
      "tag": "heal",
      "name": "治疗"
    },
    {
      "num": "06",
      "tag": "summon",
      "name": "召唤"
    }
  ],

  "buffConfig": [
    {
      "num": "01",
      "tag": "giddy",
      "name": "眩晕"
    },
    {
      "num": "02",
      "tag": "broken",
      "name": "击碎"
    },
    {
      "num": "03",
      "tag": "burnt",
      "name": "灼烧"
    },
    {
      "num": "04",
      "tag": "govern",
      "name": "支配"
    }
  ],

  "effectConfig": [
    {
      "num": "01",
      "tag": "blast",
      "name": "冲击"
    },
    {
      "num": "02",
      "tag": "multi",
      "name": "多重射击"
    },
    {
      "num": "03",
      "tag": "chain_shoot",
      "name": "弹射射击"
    },
    {
      "num": "04",
      "tag": "chain_heal",
      "name": "弹射治愈"
    }
  ]
}